primeagent/__init__.py
primeagent/__main__.py
primeagent/alembic.ini
primeagent/main.py
primeagent/memory.py
primeagent/middleware.py
primeagent/primeagent_launcher.py
primeagent/py.typed
primeagent/server.py
primeagent/settings.py
primeagent/worker.py
primeagent/alembic/README
primeagent/alembic/env.py
primeagent/alembic/script.py.mako
primeagent/alembic/versions/006b3990db50_add_unique_constraints.py
primeagent/alembic/versions/012fb73ac359_add_folder_table.py
primeagent/alembic/versions/0882f9657f22_encrypt_existing_mcp_auth_settings_.py
primeagent/alembic/versions/0ae3a2674f32_update_the_columns_that_need_to_change_.py
primeagent/alembic/versions/0b8757876a7c_.py
primeagent/alembic/versions/0d60fcbd4e8e_create_vertex_builds_table.py
primeagent/alembic/versions/182e5471b900_add_context_message.py
primeagent/alembic/versions/1a110b568907_replace_credential_table_with_variable.py
primeagent/alembic/versions/1b8b740a6fa3_remove_fk_constraint_in_message_.py
primeagent/alembic/versions/1c79524817ed_add_unique_constraints_per_user_in_.py
primeagent/alembic/versions/1cb603706752_modify_uniqueness_constraint_on_file_.py
primeagent/alembic/versions/1d90f8a0efe1_update_description_columns_type.py
primeagent/alembic/versions/1eab2c3eb45e_event_error.py
primeagent/alembic/versions/1ef9c4f3765d_.py
primeagent/alembic/versions/1f4d6df60295_add_default_fields_column.py
primeagent/alembic/versions/260dbcc8b680_adds_tables.py
primeagent/alembic/versions/29fe8f1f806b_add_missing_index.py
primeagent/alembic/versions/2ac71eb9c3ae_adds_credential_table.py
primeagent/alembic/versions/3162e83e485f_add_auth_settings_to_folder_and_merge.py
primeagent/alembic/versions/3bb0ddf32dfb_add_unique_constraints_per_user_in_flow_.py
primeagent/alembic/versions/4e5980a44eaa_fix_date_times_again.py
primeagent/alembic/versions/58b28437a398_modify_nullable.py
primeagent/alembic/versions/5ace73a7f223_new_remove_table_upgrade_op.py
primeagent/alembic/versions/631faacf5da2_add_webhook_columns.py
primeagent_base-0.1.0.dist-info/METADATA
primeagent_base-0.1.0.dist-info/WHEEL
primeagent_base-0.1.0.dist-info/entry_points.txt
primeagent_base-0.1.0.dist-info/RECORD
